android_fingerprint/__init__.py
android_fingerprint/device.py
android_fingerprint/py.typed
android_fingerprint/data/__init__.py
android_fingerprint/data/google_phones.py
android_fingerprint/types/__init__.py
android_fingerprint/types/device.py
android_fingerprint/types/device_data.py
android_fingerprint-0.6.0.dist-info/licenses/LICENSE
android_fingerprint-0.6.0.dist-info/METADATA
android_fingerprint-0.6.0.dist-info/WHEEL
android_fingerprint-0.6.0.dist-info/top_level.txt
android_fingerprint-0.6.0.dist-info/RECORD
