Metadata-Version: 2.4
Name: android-fingerprint
Version: 0.6.0
Summary: Android fingerpints provider for making requests in android based APIs
Author-email: Rune Tech <runetech2024@gmail.com>
License: The MIT License (MIT)
Project-URL: Homepage, https://github.com/runetech0/android-fingerprint.git
Project-URL: github, https://github.com/runetech0/android-fingerprint.git
Keywords: android-fingerprint,requests-fingerprint,http-fingerprints
Requires-Python: >=3.11
License-File: LICENSE
Dynamic: license-file
